ncrypt/cli.py
ncrypt/assets/embed_client.zip
ncrypt/assets/search_client.zip
ncrypt/commands/__init__.py
ncrypt/commands/cd.py
ncrypt/commands/get.py
ncrypt/commands/lcd.py
ncrypt/commands/lls.py
ncrypt/commands/lmkdir.py
ncrypt/commands/lpwd.py
ncrypt/commands/ls.py
ncrypt/commands/meta.py
ncrypt/commands/mkdir.py
ncrypt/commands/mv.py
ncrypt/commands/put.py
ncrypt/commands/pwd.py
ncrypt/commands/rm.py
ncrypt/commands/rmdir.py
ncrypt/commands/rot.py
ncrypt/commands/search.py
ncrypt/metadata/__init__.py
ncrypt/metadata/audio.py
ncrypt/metadata/image.py
ncrypt/metadata/text.py
ncrypt/utils/__init__.py
ncrypt/utils/autocomplete.py
ncrypt/utils/aws.py
ncrypt/utils/constants.py
ncrypt/utils/db_ops.py
ncrypt/utils/errors.py
ncrypt/utils/get_password.py
ncrypt/utils/suppress_output.py
ncryptai-1.0.2.dist-info/licenses/LICENSE.txt
ncryptai-1.0.2.dist-info/METADATA
ncryptai-1.0.2.dist-info/WHEEL
ncryptai-1.0.2.dist-info/entry_points.txt
ncryptai-1.0.2.dist-info/top_level.txt
ncryptai-1.0.2.dist-info/RECORD
