Metadata-Version: 2.4
Name: ncryptai
Version: 1.0.2
Summary: Privacy preserving file manager
Author-email: ncrypt <ncrypt.ai.dev@gmail.com>
Maintainer-email: ncrypt <ncrypt.ai.dev@gmail.com>
License-Expression: BSD-3-Clause
Project-URL: Homepage, https://github.com/ncrypt-ai/ncrypt
Project-URL: Roadmap, https://github.com/ncrypt-ai/ncrypt/blob/main/ROADMAP.md
Project-URL: Documentation, https://readthedocs.org
Keywords: fhe,homomorphic,encryption,privacy,security,cli,files,file manager,storage
Classifier: Development Status :: 3 - Alpha
Classifier: Environment :: Console
Classifier: Intended Audience :: Developers
Classifier: Intended Audience :: End Users/Desktop
Classifier: Natural Language :: English
Classifier: Operating System :: MacOS
Classifier: Operating System :: POSIX :: Linux
Classifier: Programming Language :: Python :: 3 :: Only
Classifier: Programming Language :: Python :: 3.11
Classifier: Topic :: Communications :: File Sharing
Classifier: Topic :: Database :: Front-Ends
Classifier: Topic :: Internet :: File Transfer Protocol (FTP)
Classifier: Topic :: Security
Classifier: Topic :: System :: Shells
Classifier: Topic :: Terminals
Requires-Python: >=3.11
License-File: LICENSE.txt
Requires-Dist: beautifulsoup4==4.13.4
Requires-Dist: boto3~=1.38.46
Requires-Dist: botocore~=1.38.46
Requires-Dist: cmd2~=2.5.2
Requires-Dist: concrete-python==2.10.0
Requires-Dist: concrete==4.18.2
Requires-Dist: cryptography~=45.0.4
Requires-Dist: einops==0.8.1
Requires-Dist: googletrans
Requires-Dist: gnureadline==8.2.13
Requires-Dist: httpx
Requires-Dist: imutils==0.5.4
Requires-Dist: keyring==25.6.0
Requires-Dist: langdetect
Requires-Dist: mmh3
Requires-Dist: ndg-httpsclient==0.5.1
Requires-Dist: nltk==3.9.1
Requires-Dist: numpy==1.26.4
Requires-Dist: openai-whisper
Requires-Dist: opencv-python==4.11.0.86
Requires-Dist: openpyxl==3.1.5
Requires-Dist: pillow~=9.4.0
Requires-Dist: pydantic
Requires-Dist: python-docx
Requires-Dist: python-pptx
Requires-Dist: PyMuPDF
Requires-Dist: sentence-transformers==3.2.0
Requires-Dist: torch==2.2.2
Requires-Dist: transformers~=4.41.0
Requires-Dist: tqdm
Provides-Extra: dev
Requires-Dist: coverage; extra == "dev"
Requires-Dist: dotenv; extra == "dev"
Requires-Dist: mypy; extra == "dev"
Requires-Dist: ruff; extra == "dev"
Provides-Extra: docs
Requires-Dist: furo; extra == "docs"
Requires-Dist: sphinx; extra == "docs"
Requires-Dist: sphinx_copybutton; extra == "docs"
Requires-Dist: sphinx-remove-toctrees; extra == "docs"
Dynamic: license-file
